acp/__init__.py
acp/client.py
acp/server.py
acp/start_server.py
coding_agent_plugin/__init__.py
coding_agent_plugin/acp/__init__.py
coding_agent_plugin/acp/client.py
coding_agent_plugin/acp/server.py
coding_agent_plugin/acp/start_server.py
coding_agent_plugin/agents/__init__.py
coding_agent_plugin/agents/base_agent.py
coding_agent_plugin/agents/coding.py
coding_agent_plugin/agents/documentation.py
coding_agent_plugin/agents/error.py
coding_agent_plugin/agents/execution.py
coding_agent_plugin/agents/file_modifier.py
coding_agent_plugin/agents/orchestrator.py
coding_agent_plugin/agents/planning.py
coding_agent_plugin/agents/task.py
coding_agent_plugin/cli/__init__.py
coding_agent_plugin/cli/main.py
coding_agent_plugin/context/__init__.py
coding_agent_plugin/context/project_context.py
coding_agent_plugin/core/config.py
coding_agent_plugin/core/database.py
coding_agent_plugin/core/logging.py
coding_agent_plugin/integrations/__init__.py
coding_agent_plugin/integrations/git_manager.py
coding_agent_plugin/managers/__init__.py
coding_agent_plugin/managers/project_manager.py
coding_agent_plugin/managers/storage_manager.py
coding_agent_plugin/mcp/__init__.py
coding_agent_plugin/mcp/server.py
coding_agent_plugin/models/__init__.py
coding_agent_plugin/models/database.py
coding_agent_plugin/models/db_models.py
coding_agent_plugin/models/project.py
coding_agent_plugin/repositories/project.py
coding_agent_plugin/schemas/__init__.py
coding_agent_plugin/schemas/project.py
coding_agent_plugin/services/__init__.py
coding_agent_plugin/services/analytics.py
coding_agent_plugin/services/intent.py
coding_agent_plugin/services/llm_service.py
coding_agent_plugin/services/project.py
coding_agent_plugin/services/prompt_service.py
coding_agent_plugin/services/quality.py
coding_agent_plugin/services/template.py
coding_agent_plugin/utils/__init__.py
coding_agent_plugin/utils/analytics_callback.py
coding_agent_plugin/utils/logger.py
coding_agent_plugin/utils/token_manager.py
agentic_coder-0.6.0.dist-info/METADATA
agentic_coder-0.6.0.dist-info/WHEEL
agentic_coder-0.6.0.dist-info/entry_points.txt
agentic_coder-0.6.0.dist-info/licenses/LICENSE
agentic_coder-0.6.0.dist-info/RECORD
