Metadata-Version: 2.4
Name: agentic-coder
Version: 0.6.0
Summary: AI-powered autonomous project creator and iterative developer
Project-URL: Homepage, https://github.com/mohamedabubasith/coding-agent
Project-URL: Documentation, https://github.com/mohamedabubasith/coding-agent#readme
Project-URL: Repository, https://github.com/mohamedabubasith/coding-agent
Project-URL: Issues, https://github.com/mohamedabubasith/coding-agent/issues
Author-email: Mohamed Abu Basith <your.email@example.com>
Maintainer-email: Mohamed Abu Basith <your.email@example.com>
License: MIT
License-File: LICENSE
Keywords: agentic,ai,autonomous,code-generation,coding-agent,llm,project-creator
Classifier: Development Status :: 3 - Alpha
Classifier: Intended Audience :: Developers
Classifier: License :: OSI Approved :: MIT License
Classifier: Programming Language :: Python :: 3
Classifier: Programming Language :: Python :: 3.10
Classifier: Programming Language :: Python :: 3.11
Classifier: Programming Language :: Python :: 3.12
Classifier: Topic :: Software Development :: Build Tools
Classifier: Topic :: Software Development :: Code Generators
Requires-Python: >=3.10
Requires-Dist: aiosqlite>=0.20.0
Requires-Dist: asyncpg>=0.29.0
Requires-Dist: black>=24.0.0
Requires-Dist: click>=8.1.0
Requires-Dist: fastapi>=0.109.0
Requires-Dist: gitpython>=3.1.0
Requires-Dist: httpx>=0.27.0
Requires-Dist: langchain-openai>=1.1.0
Requires-Dist: langchain>=1.1.0
Requires-Dist: mcp>=0.1.0
Requires-Dist: minio>=7.2.0
Requires-Dist: psycopg2-binary>=2.9.11
Requires-Dist: pydantic>=2.8.0
Requires-Dist: python-dotenv>=1.0.0
Requires-Dist: rich>=13.7.0
Requires-Dist: sqlalchemy[asyncio]>=2.0.0
Requires-Dist: typer>=0.12.0
Requires-Dist: uvicorn>=0.27.0
Provides-Extra: dev
Requires-Dist: httpx>=0.27.0; extra == 'dev'
Requires-Dist: pytest-asyncio>=0.23.0; extra == 'dev'
Requires-Dist: pytest-cov>=4.1.0; extra == 'dev'
Requires-Dist: pytest>=8.0.0; extra == 'dev'
